setup.py
illy_distributions/Binomialdistribution.py
illy_distributions/Gaussiandistribution.py
illy_distributions/Generaldistribution.py
illy_distributions/__init__.py
illy_distributions.egg-info/PKG-INFO
illy_distributions.egg-info/SOURCES.txt
illy_distributions.egg-info/dependency_links.txt
illy_distributions.egg-info/not-zip-safe
illy_distributions.egg-info/top_level.txt