Metadata-Version: 2.1
Name: illy-distributions
Version: 1.0
Summary: Gaussian and Binomial distributions
Home-page: UNKNOWN
Author: illyShelly
License: UNKNOWN
Platform: UNKNOWN
